lambdantic/Fields.py
lambdantic/__init__.py
lambdantic/version.py
lambdantic/apigateway/__init__.py
lambdantic/apigateway/exceptions.py
lambdantic/apigateway/handlers.py
lambdantic/apigateway/models.py
lambdantic/s3/__init__.py
lambdantic/s3/models.py
lambdantic/sns/__init__.py
lambdantic/sns/models.py
lambdantic/sqs/__init__.py
lambdantic/sqs/models.py
tests/.gitkeep
tests/__init__.py
tests/lambdantic/__init__.py
tests/lambdantic/apigateway/__init__.py
tests/lambdantic/apigateway/test_handler.py
tests/lambdantic/sns/test_notification.py
tests/lambdantic/sns/test_subscribe.py
tests/lambdantic/sns/test_unsubscribe.py
tests/test_example/__init__.py
tests/test_example/test_apigateway_simple.py
lambdantic-0.0.4.dist-info/LICENSE
lambdantic-0.0.4.dist-info/METADATA
lambdantic-0.0.4.dist-info/WHEEL
lambdantic-0.0.4.dist-info/top_level.txt
lambdantic-0.0.4.dist-info/zip-safe
lambdantic-0.0.4.dist-info/RECORD
