Metadata-Version: 2.1
Name: lambdantic
Version: 0.0.4
Summary: Pydantic model and lambda event handler for AWS Lambda
Home-page: https://github.com/koxudaxi/lambdantic/
Author: Koudai Aono
Author-email: koxudaxi@gmail.com
License: UNKNOWN
Platform: UNKNOWN
Requires-Python: >=3.7.0
Requires-Dist: pydantic[email,ujson] (==0.32.0)
Provides-Extra: all
Requires-Dist: pytest-runner ; extra == 'all'
Requires-Dist: setuptools-scm ; extra == 'all'
Requires-Dist: pytest ; extra == 'all'
Requires-Dist: pytest-benchmark ; extra == 'all'
Requires-Dist: pytest-cov ; extra == 'all'
Requires-Dist: pytest-mock ; extra == 'all'
Requires-Dist: mypy ; extra == 'all'
Requires-Dist: isort ; extra == 'all'
Requires-Dist: freezegun ; extra == 'all'
Requires-Dist: black ; extra == 'all'
Requires-Dist: mkdocs ; extra == 'all'
Requires-Dist: mkdocs-material ; extra == 'all'
Requires-Dist: wheel ; extra == 'all'
Requires-Dist: twine ; extra == 'all'
Requires-Dist: codecov ; extra == 'all'
Provides-Extra: ci
Requires-Dist: codecov ; extra == 'ci'
Provides-Extra: docs
Requires-Dist: mkdocs ; extra == 'docs'
Requires-Dist: mkdocs-material ; extra == 'docs'
Provides-Extra: setup
Requires-Dist: pytest-runner ; extra == 'setup'
Requires-Dist: setuptools-scm ; extra == 'setup'
Provides-Extra: test
Requires-Dist: pytest ; extra == 'test'
Requires-Dist: pytest-benchmark ; extra == 'test'
Requires-Dist: pytest-cov ; extra == 'test'
Requires-Dist: pytest-mock ; extra == 'test'
Requires-Dist: mypy ; extra == 'test'
Requires-Dist: isort ; extra == 'test'
Requires-Dist: freezegun ; extra == 'test'
Requires-Dist: black ; extra == 'test'
Provides-Extra: wheel
Requires-Dist: wheel ; extra == 'wheel'
Requires-Dist: twine ; extra == 'wheel'
